mcp_metal_price/__init__.py
mcp_metal_price/__main__.py
mcp_metal_price/server.py
mseep_mcp_metal_price-0.0.8.dist-info/licenses/LICENSE
mseep_mcp_metal_price-0.0.8.dist-info/METADATA
mseep_mcp_metal_price-0.0.8.dist-info/WHEEL
mseep_mcp_metal_price-0.0.8.dist-info/entry_points.txt
mseep_mcp_metal_price-0.0.8.dist-info/top_level.txt
mseep_mcp_metal_price-0.0.8.dist-info/RECORD
